chronosx/__init__.py
chronosx/__main__.py
chronosx/app.py
chronosx/resources/ChronosX.icns
chronosx/resources/ChronosX.iconset/icon_1024x1024.png
chronosx/resources/ChronosX.iconset/icon_128x128.png
chronosx/resources/ChronosX.iconset/icon_128x128@2x.png
chronosx/resources/ChronosX.iconset/icon_16x16.png
chronosx/resources/ChronosX.iconset/icon_16x16@2x.png
chronosx/resources/ChronosX.iconset/icon_256x256.png
chronosx/resources/ChronosX.iconset/icon_256x256@2x.png
chronosx/resources/ChronosX.iconset/icon_32x32.png
chronosx/resources/ChronosX.iconset/icon_32x32@2x.png
chronosx/resources/ChronosX.iconset/icon_512x512.png
chronosx/resources/ChronosX.iconset/icon_512x512@2x.png
chronosx/resources/ChronosX.iconset/icon_64x64.png
chronosx/resources/ChronosX.iconset/icon_64x64@2x.png
chronosx-1.0.1.dist-info/licenses/LICENSE
chronosx-1.0.1.dist-info/METADATA
chronosx-1.0.1.dist-info/WHEEL
chronosx-1.0.1.dist-info/entry_points.txt
chronosx-1.0.1.dist-info/top_level.txt
chronosx-1.0.1.dist-info/RECORD
