Metadata-Version: 2.4
Name: chronosx
Version: 1.0.1
Summary: Minimal macOS menubar chronometer with lap history
Author: albou
License-Expression: MIT
Project-URL: Homepage, https://github.com/lpalbou/chronosx
Project-URL: Repository, https://github.com/lpalbou/chronosx
Keywords: macos,menubar,chronometer,stopwatch,timer,productivity
Classifier: Development Status :: 4 - Beta
Classifier: Environment :: MacOS X
Classifier: Intended Audience :: End Users/Desktop
Classifier: Operating System :: MacOS :: MacOS X
Classifier: Programming Language :: Python :: 3
Classifier: Programming Language :: Python :: 3.9
Classifier: Programming Language :: Python :: 3.10
Classifier: Programming Language :: Python :: 3.11
Classifier: Programming Language :: Python :: 3.12
Classifier: Topic :: Utilities
Requires-Python: >=3.9
License-File: LICENSE
Requires-Dist: pyobjc-framework-Cocoa>=9.0
Provides-Extra: dev
Requires-Dist: py2app>=0.28; extra == "dev"
Requires-Dist: Pillow>=9.0; extra == "dev"
Dynamic: license-file
